Environmental_Control_HDL/environmental_control.v
`timescale 1ns/1ps

module fsm_vital_sign (
    // Clock & Reset
    input clk,
    input reset,

    // 6 Sensor Inputs (1=Risk) -> S1, S2, S3, S4, S5, S6 di tutorial lama
    input H, P, O, T, R, B, 

    // 6 Actuator Outputs (1=ON) -> A1, A2, A3, A4, A5, A6 di tutorial lama
    output reg Buzzer, LED, Vibrator, Micro_Fan, Selenoid_Valve, Infuse_Pump
);

// --- 1. Definisi Status FSM (Q1Q0) ---
// S0=00, S1=01, S2=10
parameter S0 = 2'b00; // Normal
parameter S1 = 2'b01; // Peringatan
parameter S2 = 2'b10; // Krisis Total

reg [1:0] current_state;
reg [1:0] next_state;

// --- 2. Logika Input Derivasi (A & C_Total) ---
// Logika yang diambil dari Definisi 3 Status FSM (Hal 9)
wire A;      // Risiko Apapun (OR)
wire C_Total; // Risiko Kritis Total (AND)

assign A       = H | P | O | T | R | B;
assign C_Total = H & P & O & T & R & B;

// --- 3. Logika Next State (Transisi Status) ---
always @(*) begin
    next_state = current_state; // Default: Tetap di status saat ini

    case (current_state)
        S0: begin // Normal
            if (C_Total)    next_state = S2;  // Krisis Total (1,1) -> S2
            else if (A)     next_state = S1;  // Peringatan (1,0) -> S1
            else            next_state = S0;  // Aman (0,0) -> S0
        end
        S1: begin // Peringatan
            if (C_Total)    next_state = S2;  // Krisis Total (1,1) -> S2
            else if (!A)    next_state = S0;  // Kembali Normal (0,0) -> S0
            // else (A=1, C_Total=0): next_state = S1; (Default)
        end
        S2: begin // Krisis Total
            if (!A)         next_state = S0;  // Kembali Normal (0,0) -> S0
            else if (!C_Total) next_state = S1;  // Risiko Peringatan (1,0) -> S1
            // else (A=1, C_Total=1): next_state = S2; (Default)
        end
        default: next_state = S0;
    endcase
end

// --- 4. State Register (D Flip-Flop) ---
always @(posedge clk or posedge reset) begin
    if (reset) begin
        current_state <= S0;
    end else begin
        current_state <= next_state;
    end
end

// --- 5. Logika Output Aktuator ---
// Logika diambil dari Tabel Transisi Status (Hal 10)
// Buzzer = C_Total (Ketika S_next=S2)
// Visual (LED/Vibrator) = A (Ketika S_next=S1 atau S2)
// Mitigasi = A (Ketika S_next=S1 atau S2)

always @(*) begin
    // Aktuator Visual & Buzzer (Global)
    Buzzer = C_Total; // O_Buzzer = C_Total
    LED = A;          // O_Visual = A
    Vibrator = A;     // O_Visual = A

    // Aktuator Mitigasi (Individual, dipicu saat A=1)
    // Logika individual untuk Mitigasi (Fan=T, SV=O, Pump=B) hanya aktif di status S1 atau S2 (A=1)
    if (A) begin
        Micro_Fan        = T;
        Selenoid_Valve   = O;
        Infuse_Pump      = B;
    end else begin
        Micro_Fan        = 0;
        Selenoid_Valve   = 0;
        Infuse_Pump      = 0;
    end
end

// Optional: Tambahkan output untuk memudahkan visualisasi status di GTKWave
// Anda dapat melihat reg [1:0] current_state secara langsung.

endmodule

Environmental_Control_HDL/tb_environmental_control.v
`timescale 1ns/1ps

module tb_environmental_control;

// --- Deklarasi Sinyal ---
reg clk;
reg reset;
reg H, P, O, T, R, B; // Sensor Inputs (S1-S6)
wire Buzzer, LED, Vibrator, Micro_Fan, Selenoid_Valve, Infuse_Pump; // Actuator Outputs (A1-A6)

// --- Instansiasi Unit Under Test (UUT) ---
fsm_vital_sign uut (
    .clk(clk),
    .reset(reset),
    .H(H), .P(P), .O(O), .T(T), .R(R), .B(B), // Input Sensor
    .Buzzer(Buzzer), .LED(LED), .Vibrator(Vibrator), 
    .Micro_Fan(Micro_Fan), .Selenoid_Valve(Selenoid_Valve), .Infuse_Pump(Infuse_Pump) // Output Aktuator
);

// --- Clock Generator ---
initial begin
    clk = 0;
    forever #20 clk = ~clk; // Periode clock 40ns (Frekuensi 25MHz)
end

// --- Setup Dumpfile (Untuk GTKWave) ---
initial begin
    $dumpfile("environmental_control.vcd");
    $dumpvars(0, tb_environmental_control);
end

// --- Sinyal Stimulus Test Sequence (S0 -> S1 -> S2 -> S1 -> S0) ---
initial begin
    // 1. Inisialisasi
    reset = 1; #50; // Jaga reset tetap tinggi beberapa waktu
    reset = 0; #50; // Reset Selesai. Status: S0 (Normal). Sensor: 000000. Aktuator: 000000.

    // 2. Transisi S0 -> S1 (Risiko Peringatan: H-Risk ON)
    H = 1; P = 0; O = 0; T = 0; R = 0; B = 0; // A=1, C_Total=0
    #80; // Status: S1 (Peringatan). Aktuator: Buzzer=0, Visual=1, Mitigasi=0 (karena T,O,B=0).

    // 3. Transisi S1 -> S2 (Risiko Krisis Total: Semua ON)
    H = 1; P = 1; O = 1; T = 1; R = 1; B = 1; // A=1, C_Total=1
    #80; // Status: S2 (Krisis Total). Aktuator: Buzzer=1, Visual=1, Mitigasi=1.

    // 4. Transisi S2 -> S1 (Risiko Peringatan: T, O, R Risk ON)
    H = 0; P = 0; O = 1; T = 1; R = 1; B = 0; // A=1, C_Total=0
    #80; // Status: S1 (Peringatan). Aktuator: Buzzer=0, Visual=1, Mitigasi=1 (Fan=1, SV=1, Pump=0).

    // 5. Transisi S1 -> S0 (Semua Aman)
    H = 0; P = 0; O = 0; T = 0; R = 0; B = 0; // A=0, C_Total=0
    #80; // Status: S0 (Normal). Aktuator: 000000.

    $finish;
end

endmodule

Environmental_Control_HDL/environmental_control.vcd
$date
	Wed Dec 03 07:28:02 2025
$end
$version
	Icarus Verilog
$end
$timescale
	1ps
$end
$scope module tb_environmental_control $end
$var wire 1 ! Vibrator $end
$var wire 1 " Selenoid_Valve $end
$var wire 1 # Micro_Fan $end
$var wire 1 $ LED $end
$var wire 1 % Infuse_Pump $end
$var wire 1 & Buzzer $end
$var reg 1 ' B $end
$var reg 1 ( H $end
$var reg 1 ) O $end
$var reg 1 * P $end
$var reg 1 + R $end
$var reg 1 , T $end
$var reg 1 - clk $end
$var reg 1 . reset $end
$scope module uut $end
$var wire 1 / A $end
$var wire 1 ' B $end
$var wire 1 0 C_Total $end
$var wire 1 ( H $end
$var wire 1 ) O $end
$var wire 1 * P $end
$var wire 1 + R $end
$var wire 1 , T $end
$var wire 1 - clk $end
$var wire 1 . reset $end
$var parameter 2 1 S0 $end
$var parameter 2 2 S1 $end
$var parameter 2 3 S2 $end
$var reg 1 & Buzzer $end
$var reg 1 % Infuse_Pump $end
$var reg 1 $ LED $end
$var reg 1 # Micro_Fan $end
$var reg 1 " Selenoid_Valve $end
$var reg 1 ! Vibrator $end
$var reg 2 4 current_state [1:0] $end
$var reg 2 5 next_state [1:0] $end
$upscope $end
$upscope $end
$enddefinitions $end
$comment Show the parameter values. $end
$dumpall
b10 3
b1 2
b0 1
$end
#0
$dumpvars
b0 5
b0 4
x0
x/
1.
0-
x,
x+
x*
x)
x(
x'
x&
x%
x$
x#
x"
x!
$end
#20000
1-
#40000
0-
#50000
0.
#60000
1-
#80000
0-
#100000
1!
1$
0&
b1 5
1/
00
0%
0"
0#
1-
0'
0+
0,
0)
0*
1(
#120000
0-
#140000
b1 4
1-
#160000
0-
#180000
1&
b10 5
10
1%
1"
1#
1-
1'
1+
1,
1)
1*
#200000
0-
#220000
b10 4
1-
#240000
0-
#260000
0&
b1 5
00
0%
1-
0'
0*
0(
#280000
0-
#300000
b1 4
1-
#320000
0-
#340000
0!
0$
b0 5
0/
0"
0#
1-
0+
0,
0)
#360000
0-
#380000
b0 4
1-
